wolf_ism8/__init__.py
wolf_ism8/ism8.py
wolf_ism8/ism8_constants.py
wolf_ism8/ism8_helper_functions.py
wolf_ism8-3.4.dist-info/licenses/LICENSE
wolf_ism8-3.4.dist-info/METADATA
wolf_ism8-3.4.dist-info/WHEEL
wolf_ism8-3.4.dist-info/top_level.txt
wolf_ism8-3.4.dist-info/RECORD
