Metadata-Version: 2.4
Name: wolf_ism8
Version: 3.4
Summary: Write and read data from wolf heating system via ISM8
Author-email: marcschmiedchen <marc.schmiedchen@protonmail.com>
License: MIT License
Project-URL: Repository, https://github.com/marcschmiedchen/wolf_ism8
Project-URL: Issues, https://github.com/marcschmiedchen/wolf_ism8/issues
Keywords: Home Assistant,Wolf,HVAC
Classifier: License :: OSI Approved :: MIT License
Classifier: Programming Language :: Python
Classifier: Programming Language :: Python :: 3
Classifier: Development Status :: 5 - Production/Stable
Classifier: Intended Audience :: Developers
Requires-Python: >=3.8
License-File: LICENSE
Requires-Dist: asyncio
Dynamic: license-file
